BotballKit/__init__.py
BotballKit/bot.py
BotballKit/parts.py
BotballKit-1.0.dist-info/LICENSE
BotballKit-1.0.dist-info/METADATA
BotballKit-1.0.dist-info/WHEEL
BotballKit-1.0.dist-info/top_level.txt
BotballKit-1.0.dist-info/RECORD
