Metadata-Version: 2.1
Name: BotballKit
Version: 1.0
Summary: An object-oriented wrapper for the KIPR library
Home-page: https://gitlab.com/devluke/botballkit
Author: Luke
Author-email: lukepc@protonmail.com
License: UNKNOWN
Platform: UNKNOWN
Classifier: Programming Language :: Python :: 3
Classifier: License :: OSI Approved :: GNU General Public License v3 (GPLv3)
Classifier: Operating System :: POSIX :: Linux
Requires-Python: >=3.7
